{
  "claims": {
    "hwC2mLP73zPi": {
      "runner_instance_id": "DESKTOP-NPIOPS6-13041",
      "runner_email": "andybrummer@standardbeagle.com",
      "claimed_at": "2026-05-14T19:54:00Z",
      "agent_id": "DESKTOP-NPIOPS6-13041",
      "parent_loop_id": "epYVBosC0i3a",
      "purpose": "MM Financial 3/4 — renew/record-payment workflow endpoints + record-payment screen",
      "source_event": {
        "loop_id": "epYVBosC0i3a",
        "task_id": "hwC2mLP73zPi",
        "conversation_id": null
      }
    }
  }
}
